utctime/__init__.py
utctime/py.typed
utctime/utctime.py
utctime-0.2.0b0.dist-info/LICENSE
utctime-0.2.0b0.dist-info/METADATA
utctime-0.2.0b0.dist-info/WHEEL
utctime-0.2.0b0.dist-info/top_level.txt
utctime-0.2.0b0.dist-info/RECORD
