Metadata-Version: 2.1
Name: utctime
Version: 0.2.0b0
Summary: A simple and type-safe way of working with UTC datetimes and ISO 8601 strings.
License: MIT License
Project-URL: Documentation, https://utctime.readthedocs.io
Project-URL: Source, https://github.com/dmayo3/utctime
Keywords: utc,datetime,iso,iso8601,time,utility,util
Classifier: Development Status :: 3 - Alpha
Classifier: Natural Language :: English
Classifier: Operating System :: OS Independent
Classifier: Intended Audience :: Developers
Classifier: License :: OSI Approved :: MIT License
Classifier: Programming Language :: Python
Classifier: Programming Language :: Python :: 3
Classifier: Programming Language :: Python :: 3.9
Classifier: Programming Language :: Python :: 3.10
Classifier: Programming Language :: Python :: 3.11
Classifier: Programming Language :: Python :: 3.12
Classifier: Programming Language :: Python :: 3.13
Classifier: Programming Language :: Python :: 3 :: Only
Classifier: Programming Language :: Python :: Implementation :: CPython
Classifier: Topic :: Software Development :: Libraries
Classifier: Topic :: Utilities
Classifier: Typing :: Typed
Requires-Python: >=3.9
License-File: LICENSE
Provides-Extra: docs
Requires-Dist: sphinx-rtd-theme>=1.2.0; extra == "docs"
Requires-Dist: pytest>=6.2.0; extra == "docs"
